MANIFEST.in
README.txt
setup.cfg
setup.py
docs/lgpl-3.0.txt
languagedet/__init__.py
languagedet/detector.py
languagedet/mixed.py
languagedet/stopwords.py
languagedet/textcat.py
languagedet.egg-info/PKG-INFO
languagedet.egg-info/SOURCES.txt
languagedet.egg-info/dependency_links.txt
languagedet.egg-info/entry_points.txt
languagedet.egg-info/top_level.txt
languagedet.egg-info/zip-safe
languagedet/data/da.txt
languagedet/data/de.txt
languagedet/data/en.txt
languagedet/data/es.txt
languagedet/data/fi.txt
languagedet/data/fr.txt
languagedet/data/hu.txt
languagedet/data/it.txt
languagedet/data/nl.txt
languagedet/data/no.txt
languagedet/data/pt.txt
languagedet/data/ru.txt
languagedet/data/stopwords.pickle
languagedet/data/sv.txt
languagedet/data/textcat.conf
languagedet/data/tr.txt
src/languagedet._textcat.c