Metadata-Version: 1.0
Name: languagedet
Version: 0.1.1
Summary: Python package for language detection.
Home-page: UNKNOWN
Author: Karel Antonio Verdecia Ortiz
Author-email: kverdecia@uci.cu
License: LGPL3
Platform: UNKNOWN
